tfont/__init__.py
tfont/_version.py
tfont/converters/__init__.py
tfont/converters/tfontConverter.py
tfont/converters/ufoConverter.py
tfont/objects/__init__.py
tfont/objects/anchor.py
tfont/objects/axis.py
tfont/objects/component.py
tfont/objects/feature.py
tfont/objects/font.py
tfont/objects/glyph.py
tfont/objects/guideline.py
tfont/objects/instance.py
tfont/objects/layer.py
tfont/objects/master.py
tfont/objects/misc.py
tfont/objects/path.py
tfont/objects/point.py
tfont/util/__init__.py
tfont/util/bezierMath.py
tfont/util/slice.py
tfont/util/tracker.py
tfont-0.1.1.dist-info/LICENSE
tfont-0.1.1.dist-info/METADATA
tfont-0.1.1.dist-info/WHEEL
tfont-0.1.1.dist-info/top_level.txt
tfont-0.1.1.dist-info/RECORD
